{
    "titleIcon": "https://gitee.com/au_t/cym-file/raw/master/titleIcon.jpg",
    "imageAndTextList": [
        {
            "leftImage": "https://gitee.com/au_t/cym-file/raw/master/favicon.jpg",
            "rightText": "【关于我们】\n  江西宜春涂氏茶油苗批发，我们的油茶苗100%经过嫁接，拥有七年的栽培茶油苗经验，主要批发存活率高的两年高大茶油苗。丰产后可产果3000-4000斤、茶油50-70公斤。",
            "text": "我们本着“人以诚为本、商以信为先”的经营理念，每年栽培投资百万元栽培江西省农科院的嫁接茶油苗，栽培的两年高大茶油苗不但供应本省且远销广东、浙江、福建、湖南、湖北、安徽、广西、四川等全国油茶主产区。涂氏茶油苗批发每年茶树苗产量数百万元人民币，可长期合作提供茶树苗。欢迎致电协商。",
            "leftImageWidth": "210px",
            "leftImageHeight": "150px",
            "rightTextWidth": "430px",
            "leftImageHeight": "150px",
            "textHeight": "180px"
        },
        {
            "leftImage": "https://gitee.com/au_t/cym-file/raw/master/images/introduction/price.jpg",
            "rightText": "【关于价格优惠】\n  1、10000株以内价格按第4点标价销售，包邮；\n2、10000株以上价格可来人来电具体磋商，我方尽量让利，并可送货上门;",
            "text": "3、欢迎各位亲们前来我们栽培点参观考察，以眼见为实，以实物为准，以免上当受骗，做到心中有数、放心购苗。\n4、100-499棵 ¥2.00; 500-999棵 ¥1.70; 10000-1000棵 ¥1.40 株高25-90cm，可以长期合作提供茶树苗，欢迎致电咨询。",
            "leftImageWidth": "210px",
            "leftImageHeight": "150px",
            "rightTextWidth": "430px",
            "leftImageHeight": "150px",
            "textHeight": "180px"
        },
        {
            "leftImage": "https://gitee.com/au_t/cym-file/raw/master/images/introduction/quality.jpg",
            "rightText": "【关于苗木质量】\n  1、我们的油茶苗都是国家和省级审定的优良品种，三年挂果五年丰产，丰产后可产果3000-4000斤、茶油50-70公斤; ",
            "text": "2、我们的油茶苗100%经过嫁接，假一赔十，确保真苗。各位亲们千万不要贪图便宜购买没有嫁接的假油茶苗，俗话说“选错一年苗，白流五年汗”;\n  3、我们合作社创建于1999年，是江西省林科院定点育苗单位，从事油茶苗专业培育十多年，所以各位亲们在我们合作社购买的油茶苗质量放心；\n  4、我们严格按照国家一级苗标准为各位亲们提供优良油茶苗，具体规格如下：\n  （1）一年生油茶裸苗：高度10cm以上，地茎粗0.2cm以上；\n  （2）二年生油茶裸根苗，高度30cm以上，地茎粗0.3cm以上；\n  （3）三年生油茶裸根苗，高度30cm以上，地茎粗0.4cm以上；\n  （4）一年生油茶容器杯苗，高度8cm以上，地茎粗0.2cm以上；\n  （5）二年生油茶容器杯苗，高度20cm以上，地茎粗0.3cm以上； \n 一级优良油茶苗，品种纯度须达90% 以上，不带检疫性病害，嫁接口充分愈合，主干充分木质化，具有原品种固有之颜色。",
            "leftImageWidth": "210px",
            "leftImageHeight": "150px",
            "rightTextWidth": "430px",
            "leftImageHeight": "150px",
            "textHeight": "540px"
        },
        {
            "leftImage": "https://gitee.com/au_t/cym-file/raw/master/images/introduction/planting.jpg",
            "rightText": "【关于油茶种植】\n1、选地：油茶宜选择土壤深厚(80厘米以上)、疏松、排水良好、向阳的地区，PH值5~6微酸性的沙质壤土，轻粘壤土为宜。碱性土不宜选作油茶造林地。 ",
            "text": "2、整地：旱地作垄打穴，垄宽1米，高15厘米，打穴规格40×40×40厘米；坡度小于15度的山地可直接按40×40×40厘米的规格打穴；坡度大于15度的山地沿等高线水平开带，外高内地，带宽2米，带间距3米，带上按株距2米定点打穴，规格为40×40×50厘米。\n3、下基肥与回填：造林前一个月，在壕穴内施放农家肥或复合肥（每穴半斤至一斤，每亩略计100斤），然后回填表土（以免肥分流失），复土高出地表10-15厘米，将穴填满成馒头形。基肥应均施深埋，栽苗时不能让苗根接触农家肥或化肥，以免（烧）根。绝对禁止栽苗时施肥，且施足基肥的林地，第一年不要再施化肥，第二年起可适当追施化肥，切记！\n4、苗木移栽：栽植前用苗根蘸生根粉（一包生根粉用60斤水拌黄泥加5斤钙镁磷肥和成泥浆），两年生苗可先打去少量的老叶，以减少水分的蒸发；栽植的具体密度，按株行距2×3米，亩栽120株左右；栽植时间为12月下旬—3月底（冬末-春季）为宜，因为这个时候气温低（特别是大部分植物进入休眠期），有利于根系伤口的愈合，促进次年的长势。栽得太迟，苗木根部所积累的养分，既要供应芽梢生长，又要供应根部恢复伤势，会出现营养供应短缺，导致苗木生产缓慢或死亡；栽苗时要根据天气变化，选择雨后阴天栽植，天旱土干时不栽，若栽后2—3天内能下雨效果更佳；栽植要求做到栽正、舒根（回土后将苗往上轻放）、踏实（一定要踩紧，再在苗四周护些细土成窝形，以利保水）、深栽（一年生苗盖土超过嫁接口1—2厘米，两年生苗2—3厘米），栽后浇水一次定根水，在苗基部覆盖稻草防冻保湿，以提高苗木成活率。\n5、后期抚育：苗木栽植后要勤于管理，经常除草、松土、施肥，油茶种植好不好全靠后期管理。前期（前3年）需要让树冠生长，所以建议前3年把花苞和幼果摘掉，防止养分流失影响树冠的生长，有条件的地方可套种农作物。每年均要对油茶树进行整修，打顶和把见不到阳光的枝条剪掉，最后的树形要既能接受阳光又有利于空气流动。",
            "leftImageWidth": "210px",
            "leftImageHeight": "150px",
            "rightTextWidth": "430px",
            "leftImageHeight": "150px",
            "textHeight": "900px"
        }
    ],
    "priceList": [
        {
            "quantity": "1-100棵",
            "price": "¥5.00"
        },
        {
            "quantity": "100-499棵",
            "price": "¥2.00"
        },
        {
            "quantity": "500-999棵",
            "price": "¥1.70"
        },
        {
            "quantity": "≥1000棵",
            "price": "¥1.40"
        }
    ]
}
